README.rst
ez_setup.py
setup.py
vote/__init__.py
vote/__main__.py
vote/image_poll.py
vote/main.py
vote/polls.py
vote/reddit_post.py
vote/straw_poll.py
vote/version.py
vote.egg-info/PKG-INFO
vote.egg-info/SOURCES.txt
vote.egg-info/dependency_links.txt
vote.egg-info/entry_points.txt
vote.egg-info/requires.txt
vote.egg-info/top_level.txt