Metadata-Version: 1.1
Name: vote
Version: 1.0.1
Summary: A command line utility to vote on online polls.
Home-page: http://pypi.python.org/pypi/vote/
Author: Amol Umrale
Author-email: babaiscool@gmail.com
License: UNKNOWN
Platform: UNKNOWN
Classifier: Development Status :: 4 - Beta
Classifier: Environment :: Console
Classifier: License :: OSI Approved :: MIT License
Classifier: Natural Language :: English
Classifier: Operating System :: Microsoft :: Windows
Classifier: Programming Language :: Python :: 3.4
